deep_plots/__init__.py
deep_plots/plot.py
deep_plots/wrangle.py
deep_plots-0.1.1.dist-info/METADATA
deep_plots-0.1.1.dist-info/RECORD
deep_plots-0.1.1.dist-info/WHEEL
deep_plots-0.1.1.dist-info/top_level.txt
