Metadata-Version: 2.1
Name: deep-plots
Version: 0.1.1
Summary: Visualize Your Deep Learning Training in Static Graphics
Home-page: https://github.com/jfilter/deep-plots
Author: Johannes Filter
Author-email: hi@jfilter.de
License: MIT
Platform: UNKNOWN
Classifier: Topic :: Scientific/Engineering :: Visualization
Classifier: Topic :: Scientific/Engineering :: Artificial Intelligence
Classifier: Programming Language :: Python :: 3.5
Classifier: Programming Language :: Python :: 3.6
Classifier: Programming Language :: Python :: 2.7
Classifier: License :: OSI Approved :: MIT License
Classifier: Development Status :: 3 - Alpha
Requires-Dist: plotnine (==0.3.*)
Requires-Dist: pandas (==0.23.*)
